04_Microarchitecture/01_Single_Cycle_RISCV_Processor/dff_pc.v
module dff_pc (
    input             clk,
    input             rst_n,      // Active-low asynchronous reset 
    input      [31:0] pc_next,    // next PC address
    output reg [31:0] pc          // current PC address
);

    
    always @(posedge clk or negedge rst_n) begin
        if (!rst_n) begin
            pc <= 32'h0000_1000;
        end else begin
            pc <= pc_next;        //every cylce pc =pc_next
        end
    end

endmodule

04_Microarchitecture/01_Single_Cycle_RISCV_Processor/tb_dff_pc.v
`timescale 1ns / 1ps

module tb_dff_pc;

    // 1. Declare stimulus signals
    reg         clk;
    reg         rst_n;
    reg  [31:0] pc_next;
    wire [31:0] pc;

    // 2. Instantiate Device Under Test (DUT)
    dff_pc uut (
        .clk(clk),
        .rst_n(rst_n),
        .pc_next(pc_next),
        .pc(pc)
    );

    // 3. Generate 100MHz clock (10ns period)
    always #5 clk = ~clk;

    // 4. Test stimulus
    initial begin
        $dumpfile("dff_pc.vcd");
        $dumpvars(0, tb_dff_pc);

        $monitor("Time=%0t | rst_n=%b | pc_next=0x%h | pc=0x%h",
                 $time, rst_n, pc_next, pc);

        // Initialize signals
        clk     = 0;
        rst_n   = 0;      // Assert reset
        pc_next = 32'h0000_1000;

        #12;
        rst_n   = 1;      // Release reset

        // Test Case 1: Sequential instruction fetch (PC increments by 4)
        @(negedge clk);
        pc_next = 32'h0000_1004;

        @(negedge clk);
        pc_next = 32'h0000_1008;

        @(negedge clk);
        pc_next = 32'h0000_100C;

        // Test Case 2: Asynchronous reset verification during operation
        #3;
        rst_n = 0;        // Reset triggered asynchronously

        #7;
        rst_n = 1;        // Release reset again
        @(negedge clk);
        pc_next = 32'h0000_2000;

        #20;
        $finish;
    end

endmodule

04_Microarchitecture/01_Single_Cycle_RISCV_Processor/dff_pc.vcd
$date
	Fri Sep 11 16:17:47 2026
$end
$version
	Icarus Verilog
$end
$timescale
	1ps
$end
$scope module tb_dff_pc $end
$var wire 32 ! pc [31:0] $end
$var reg 1 " clk $end
$var reg 32 # pc_next [31:0] $end
$var reg 1 $ rst_n $end
$scope module uut $end
$var wire 1 " clk $end
$var wire 32 % pc_next [31:0] $end
$var wire 1 $ rst_n $end
$var reg 32 & pc [31:0] $end
$upscope $end
$upscope $end
$enddefinitions $end
$comment Show the parameter values. $end
$dumpall
$end
#0
$dumpvars
b0 &
b1000000000000 %
0$
b1000000000000 #
0"
b0 !
$end
#5000
1"
#10000
0"
#12000
1$
#15000
b1000000000000 !
b1000000000000 &
1"
#20000
b1000000000100 #
b1000000000100 %
0"
#25000
b1000000000100 !
b1000000000100 &
1"
#30000
b1000000001000 #
b1000000001000 %
0"
#35000
b1000000001000 !
b1000000001000 &
1"
#40000
b1000000001100 #
b1000000001100 %
0"
#43000
b0 !
b0 &
0$
#45000
1"
#50000
b10000000000000 #
b10000000000000 %
0"
1$
#55000
b10000000000000 !
b10000000000000 &
1"
